debut/__init__.py
debut/contents.py
debut/copyright.py
debut/coverage.py
debut/debcon.py
debut/deps.py
debut/package.py
debut/unsign.py
debut/unsign.py.ABOUT
debut/unsign.py.LICENSE
debut/utils.py
debut/version.py
debut/version.py.ABOUT
debut/version.py.LICENSE
debut-0.9.9.dist-info/CHANGELOG.rst
debut-0.9.9.dist-info/METADATA
debut-0.9.9.dist-info/NOTICE
debut-0.9.9.dist-info/README.rst
debut-0.9.9.dist-info/WHEEL
debut-0.9.9.dist-info/apache-2.0.LICENSE
debut-0.9.9.dist-info/bsd-new.LICENSE
debut-0.9.9.dist-info/mit.LICENSE
debut-0.9.9.dist-info/top_level.txt
debut-0.9.9.dist-info/RECORD
