Metadata-Version: 2.1
Name: debut
Version: 0.9.9
Summary: Utilities to parse Debian package, copyright and control files.
Home-page: https://github.com/nexB/debut
Author: nexB. Inc. and others
Author-email: info@aboutcode.org
License: Apache-2.0 AND BSD-3-Clause AND MIT
Keywords: debian,deb822,copyright,package,dependency,license,licensing,dep5,control,dsc,python-debian,dpkg,libapt
Platform: UNKNOWN
Classifier: Development Status :: 5 - Production/Stable
Classifier: Intended Audience :: Developers
Classifier: Programming Language :: Python
Classifier: Programming Language :: Python :: 3
Classifier: Programming Language :: Python :: 3.6
Classifier: Programming Language :: Python :: 3.7
Classifier: Programming Language :: Python :: 3.8
Classifier: Programming Language :: Python :: 3.9
Classifier: Topic :: Software Development
Classifier: Topic :: Utilities
Requires-Dist: chardet (>=3.0.0)
Requires-Dist: attrs (>=19.2)
